home_link/__init__.py
home_link/components/__init__.py
home_link/components/abstract_component.py
home_link/components/http.py
home_link/components/mqtt.py
home_link/config.py
home_link/firebase.py
home_link/http_server.py
home_link/main.py
home_link/models.py
home_link/parsers/__init__.py
home_link/parsers/abstract_parser.py
home_link/parsers/json.py
home_link/parsers/shelly.py
home_link/parsers/value.py
home_link-0.1.1.dist-info/LICENSE
home_link-0.1.1.dist-info/METADATA
home_link-0.1.1.dist-info/WHEEL
home_link-0.1.1.dist-info/entry_points.txt
home_link-0.1.1.dist-info/RECORD
